{"data":{"type":"project","id":"Open Austin/open-austin-logo","links":{"self":"/organizations/Open Austin/projects/open-austin-logo.json"},"attributes":{"code_url":"https://github.com/open-austin/open-austin-logo","description":"Artwork for the Open Austin logo","git_branch":"master","git_url":"git://github.com/open-austin/open-austin-logo.git","last_pushed_within":"over_a_year","name":"open-austin-logo","open_issues_within":10,"organization_name":"Open Austin"},"relationships":{"organization":{"data":{"type":"organization","id":"Open Austin"},"links":{"related":"/organizations/Open Austin.json"}}}}}