{"data":{"type":"project","id":"Data SF/Geojson-to-Socrata","links":{"self":"/organizations/Data SF/projects/Geojson-to-Socrata.json"},"attributes":{"code_url":"https://github.com/DataSF/Geojson-to-Socrata","description":"Uploads geojson files to Socrata using standard API calls","git_branch":"master","git_url":"git://github.com/DataSF/Geojson-to-Socrata.git","last_pushed_within":"over_a_year","name":"Geojson-to-Socrata","organization_name":"Data SF","topics":["etl","extract","load","transform"]},"relationships":{"organization":{"data":{"type":"organization","id":"Data SF"},"links":{"related":"/organizations/Data SF.json"}}}}}