{"data":{"type":"project","id":"Code for Puerto Rico/municipios-api","links":{"self":"/organizations/Code for Puerto Rico/projects/municipios-api.json"},"attributes":{"code_url":"https://github.com/Code4PuertoRico/municipios-api","description":"Simple Flask API for getting distance and adjacency information on Puerto Rico's municipalities","git_branch":"master","git_url":"git://github.com/Code4PuertoRico/municipios-api.git","last_pushed_within":"year","link_url":"https://municipios.rauln.com","name":"municipios-api","open_issues_within":10,"organization_name":"Code for Puerto Rico","topics":["flask-api","graph-algorithms","municipalities","puerto-rico","puerto-rico-municipalities","zappa","zappa-flask"]},"relationships":{"organization":{"data":{"type":"organization","id":"Code for Puerto Rico"},"links":{"related":"/organizations/Code for Puerto Rico.json"}}}}}