{"data":{"type":"project","id":"Code for Puerto Rico/suministrospr-web-scraper","links":{"self":"/organizations/Code for Puerto Rico/projects/suministrospr-web-scraper.json"},"attributes":{"code_url":"https://github.com/Code4PuertoRico/suministrospr-web-scraper","description":"Web scraper for the old SuministrosPR.com website.","git_branch":"master","git_url":"git://github.com/Code4PuertoRico/suministrospr-web-scraper.git","name":"suministrospr-web-scraper"},"relationships":{"organization":{"data":{"type":"organization","id":"Code for Puerto Rico"},"links":{"related":"/organizations/Code for Puerto Rico.json"}}}}}