{"data":{"type":"project","id":"Code4PuertoRico/codeofconduct","links":{"self":"/organizations/Code4PuertoRico/projects/codeofconduct.json"},"attributes":{"code_url":"https://github.com/Code4PuertoRico/codeofconduct","description":"Code for America's Code of Conduct","git_branch":"master","git_url":"git://github.com/Code4PuertoRico/codeofconduct.git","name":"codeofconduct"},"relationships":{"organization":{"data":{"type":"organization","id":"Code4PuertoRico"},"links":{"related":"/organizations/Code4PuertoRico.json"}}}}}