{"data":{"type":"project","id":"Code for Greenville/trolley-tracker-api-dot-net","links":{"self":"/organizations/Code for Greenville/projects/trolley-tracker-api-dot-net.json"},"attributes":{"code_url":"https://github.com/codeforgreenville/trolley-tracker-api-dot-net","description":"API for tracking Greenville's trolleys with .NET","git_branch":"master","git_url":"git://github.com/codeforgreenville/trolley-tracker-api-dot-net.git","last_pushed_within":"year","name":"trolley-tracker-api-dot-net","open_issues_within":10,"organization_name":"Code for Greenville"},"relationships":{"organization":{"data":{"type":"organization","id":"Code for Greenville"},"links":{"related":"/organizations/Code for Greenville.json"}}}}}