{"data":{"type":"project","id":"Open Eugene/little-help-app","links":{"self":"/organizations/Open Eugene/projects/little-help-app.json"},"attributes":{"code_url":"https://github.com/OpenEugene/little-help-app","description":"The mobile centric version of The Little Help Book.","git_branch":"main","git_url":"git://github.com/OpenEugene/little-help-app.git","last_pushed_within":"year","name":"little-help-app","organization_name":"Open Eugene"},"relationships":{"organization":{"data":{"type":"organization","id":"Open Eugene"},"links":{"related":"/organizations/Open Eugene.json"}}}}}