{"data":{"type":"project","id":"Open Wichita/comport","links":{"self":"/organizations/Open Wichita/projects/comport.json"},"attributes":{"code_url":"https://github.com/openwichita/comport","description":"Comport is a tool for law enforcement agencies to open their data and be accountable to their citizens.","git_branch":"master","git_url":"git://github.com/openwichita/comport.git","last_pushed_within":"over_a_year","link_url":"https://www.projectcomport.org","name":"comport","organization_name":"Open Wichita"},"relationships":{"organization":{"data":{"type":"organization","id":"Open Wichita"},"links":{"related":"/organizations/Open Wichita.json"}}}}}