{"data":{"type":"organization","id":"18F","links":{"self":"/organizations/18F.json"},"attributes":{"city":"San Francisco, CA","latitude":"37.7759","longitude":"-122.4137","name":"18F","projects_list_url":"https://github.com/18f","rss":"https://18f.gsa.gov/feed.xml","tags":["Government"],"type":"Government","website":"https://18f.gsa.gov/","location":{"city":"San Francisco","continent":"North America","country":"USA","state":"California","coordinates":{"latitude":"37.7759","longitude":"-122.4137"}}}}}