{"data":{"type":"organization","id":"Code4PuertoRico","links":{"self":"/organizations/Code4PuertoRico.json"},"attributes":{"city":"San Juan, PR","events_url":"http://code4puertorico.org/events.html","latitude":"18.4661","longitude":"-66.1160","name":"Code4PuertoRico","projects_list_url":"https://github.com/Code4PuertoRico","tags":["Brigade"],"type":"Brigade","website":"http://code4puertorico.org/","location":{"city":"San Juan","continent":"North America","country":"USA","state":"Puerto Rico","coordinates":{"latitude":"18.4661","longitude":"-66.1160"}}}}}