{"data":{"type":"project","id":"Milwaukee Data Initiative/mdi-website","links":{"self":"/organizations/Milwaukee Data Initiative/projects/mdi-website.json"},"attributes":{"code_url":"https://github.com/milwaukeedata/mdi-website","description":"The Milwaukee Data Initiative Web Site","git_branch":"master","git_url":"git://github.com/milwaukeedata/mdi-website.git","last_pushed_within":"over_a_year","name":"mdi-website","organization_name":"Milwaukee Data Initiative"},"relationships":{"organization":{"data":{"type":"organization","id":"Milwaukee Data Initiative"},"links":{"related":"/organizations/Milwaukee Data Initiative.json"}}}}}