{"data":{"type":"project","id":"Code for Australia/civic-makers-melbourne","links":{"self":"/organizations/Code for Australia/projects/civic-makers-melbourne.json"},"attributes":{"code_url":"https://github.com/CodeforAustralia/civic-makers-melbourne","git_branch":"master","git_url":"git://github.com/CodeforAustralia/civic-makers-melbourne.git","last_pushed_within":"over_a_year","name":"civic-makers-melbourne","organization_name":"Code for Australia"},"relationships":{"organization":{"data":{"type":"organization","id":"Code for Australia"},"links":{"related":"/organizations/Code for Australia.json"}}}}}