{"data":{"type":"project","id":"Code for Europe/Change-By-Us","links":{"self":"/organizations/Code for Europe/projects/Change-By-Us.json"},"attributes":{"code_url":"https://github.com/codeforeurope/Change-By-Us","description":"A new way to share ideas, do projects, and make our cities better","git_branch":"master","git_url":"git://github.com/codeforeurope/Change-By-Us.git","last_pushed_within":"over_a_year","link_url":"changeby.us","name":"Change-By-Us","open_issues_within":10,"organization_name":"Code for Europe"},"relationships":{"organization":{"data":{"type":"organization","id":"Code for Europe"},"links":{"related":"/organizations/Code for Europe.json"}}}}}