{"data":{"type":"project","id":"Code for Europe/wiki","links":{"self":"/organizations/Code for Europe/projects/wiki.json"},"attributes":{"code_url":"https://github.com/codeforeurope/wiki","description":"Common wiki for Code4Europe","git_branch":"master","git_url":"git://github.com/codeforeurope/wiki.git","last_pushed_within":"over_a_year","name":"wiki","organization_name":"Code for Europe"},"relationships":{"organization":{"data":{"type":"organization","id":"Code for Europe"},"links":{"related":"/organizations/Code for Europe.json"}}}}}