{"data":{"type":"project","id":"Code for Denver/rmmfi-form","links":{"self":"/organizations/Code for Denver/projects/rmmfi-form.json"},"attributes":{"code_url":"https://github.com/codefordenver/rmmfi-form","description":"Volunteer Entry form for Events","git_branch":"master","git_url":"git://github.com/codefordenver/rmmfi-form.git","last_pushed_within":"over_a_year","name":"rmmfi-form","organization_name":"Code for Denver"},"relationships":{"organization":{"data":{"type":"organization","id":"Code for Denver"},"links":{"related":"/organizations/Code for Denver.json"}}}}}