{"data":{"type":"project","id":"18F/formservice-hud903","links":{"self":"/organizations/18F/projects/formservice-hud903.json"},"attributes":{"code_url":"https://github.com/18F/formservice-hud903","git_branch":"develop","git_url":"git://github.com/18F/formservice-hud903.git","last_pushed_within":"week","name":"formservice-hud903","open_issues_within":100,"organization_name":"18F"},"relationships":{"organization":{"data":{"type":"organization","id":"18F"},"links":{"related":"/organizations/18F.json"}}}}}