{"data":{"type":"project","id":"OpenUp/org-handbook-gitbook","links":{"self":"/organizations/OpenUp/projects/org-handbook-gitbook.json"},"attributes":{"code_url":"https://github.com/OpenUpSA/org-handbook-gitbook","description":"Synced git repo of our organisational handbook gitbook","git_branch":"master","git_url":"git://github.com/OpenUpSA/org-handbook-gitbook.git","last_pushed_within":"year","name":"org-handbook-gitbook","organization_name":"OpenUp"},"relationships":{"organization":{"data":{"type":"organization","id":"OpenUp"},"links":{"related":"/organizations/OpenUp.json"}}}}}