{"data":{"type":"project","id":"OpenUp/wazimap-adh-data","links":{"self":"/organizations/OpenUp/projects/wazimap-adh-data.json"},"attributes":{"code_url":"https://github.com/OpenUpSA/wazimap-adh-data","description":"Scripts and jupyter notebooks to prepare data for upload to wazimap for the Africa Data Hub project","git_branch":"main","git_url":"git://github.com/OpenUpSA/wazimap-adh-data.git","last_pushed_within":"year","name":"wazimap-adh-data","organization_name":"OpenUp"},"relationships":{"organization":{"data":{"type":"organization","id":"OpenUp"},"links":{"related":"/organizations/OpenUp.json"}}}}}