{"data":{"type":"project","id":"Code for Pittsburgh/snowplowlatlngcount","links":{"self":"/organizations/Code for Pittsburgh/projects/snowplowlatlngcount.json"},"attributes":{"code_url":"https://github.com/CodeForPittsburgh/snowplowlatlngcount","git_branch":"master","git_url":"git://github.com/CodeForPittsburgh/snowplowlatlngcount.git","name":"snowplowlatlngcount"},"relationships":{"organization":{"data":{"type":"organization","id":"Code for Pittsburgh"},"links":{"related":"/organizations/Code for Pittsburgh.json"}}}}}