{"data":{"type":"project","id":"Code for Ghana/feinstaub-api","links":{"self":"/organizations/Code for Ghana/projects/feinstaub-api.json"},"attributes":{"code_url":"https://github.com/CodeForAfrica/feinstaub-api","description":"Django project to store sensor pushed via REST api","git_branch":"master","git_url":"git://github.com/CodeForAfrica/feinstaub-api.git","last_pushed_within":"year","name":"feinstaub-api","organization_name":"Code for Ghana"},"relationships":{"organization":{"data":{"type":"organization","id":"Code for Ghana"},"links":{"related":"/organizations/Code for Ghana.json"}}}}}