{"data":{"type":"project","id":"Open Data Delaware/food-bank-sttp","links":{"self":"/organizations/Open Data Delaware/projects/food-bank-sttp.json"},"attributes":{"code_url":"https://github.com/OpenDataDE/food-bank-sttp","git_branch":"master","git_url":"git://github.com/OpenDataDE/food-bank-sttp.git","last_pushed_within":"over_a_year","name":"food-bank-sttp","open_issues_within":100,"organization_name":"Open Data Delaware"},"relationships":{"organization":{"data":{"type":"organization","id":"Open Data Delaware"},"links":{"related":"/organizations/Open Data Delaware.json"}}}}}