{"data":{"type":"project","id":"Open Data Delaware/renovatedODDEWebsite","links":{"self":"/organizations/Open Data Delaware/projects/renovatedODDEWebsite.json"},"attributes":{"code_url":"https://github.com/OpenDataDE/renovatedODDEWebsite","description":"a home for the in-progress source code for the renovated ODDE website: www.opendatadelaware.com","git_branch":"master","git_url":"git://github.com/OpenDataDE/renovatedODDEWebsite.git","last_pushed_within":"over_a_year","name":"renovatedODDEWebsite","organization_name":"Open Data Delaware"},"relationships":{"organization":{"data":{"type":"organization","id":"Open Data Delaware"},"links":{"related":"/organizations/Open Data Delaware.json"}}}}}