{"data":{"type":"project","id":"Code for America/cfa-wufoo","links":{"self":"/organizations/Code for America/projects/cfa-wufoo.json"},"attributes":{"code_url":"https://github.com/codeforamerica/cfa-wufoo","description":"A custom css stylesheet for Code for America Wufoo forms.","git_branch":"gh-pages","git_url":"git://github.com/codeforamerica/cfa-wufoo.git","last_pushed_within":"over_a_year","name":"cfa-wufoo","open_issues_within":10,"organization_name":"Code for America"},"relationships":{"organization":{"data":{"type":"organization","id":"Code for America"},"links":{"related":"/organizations/Code for America.json"}}}}}