{"data":{"type":"project","id":"Code for America/networkplatform","links":{"self":"/organizations/Code for America/projects/networkplatform.json"},"attributes":{"code_url":"https://github.com/codeforamerica/networkplatform","description":"A meta repo to gather the work on the network platform.","git_branch":"master","git_url":"git://github.com/codeforamerica/networkplatform.git","last_pushed_within":"over_a_year","link_url":"https://waffle.io/codeforamerica/networkplatform","name":"networkplatform","organization_name":"Code for America"},"relationships":{"organization":{"data":{"type":"organization","id":"Code for America"},"links":{"related":"/organizations/Code for America.json"}}}}}