{"data":{"type":"project","id":"Code for America/transparencyjobs","links":{"self":"/organizations/Code for America/projects/transparencyjobs.json"},"attributes":{"code_url":"https://github.com/codeforamerica/transparencyjobs","description":"A job listing site for the transparency community","git_branch":"master","git_url":"git://github.com/codeforamerica/transparencyjobs.git","last_pushed_within":"over_a_year","link_url":"http://transparencyjobs.com","name":"transparencyjobs","organization_name":"Code for America"},"relationships":{"organization":{"data":{"type":"organization","id":"Code for America"},"links":{"related":"/organizations/Code for America.json"}}}}}