{"data":{"type":"project","id":"Code for America/vallejo-midyear-report","links":{"self":"/organizations/Code for America/projects/vallejo-midyear-report.json"},"attributes":{"code_url":"https://github.com/codeforamerica/vallejo-midyear-report","git_branch":"gh-pages","git_url":"git://github.com/codeforamerica/vallejo-midyear-report.git","name":"vallejo-midyear-report"},"relationships":{"organization":{"data":{"type":"organization","id":"Code for America"},"links":{"related":"/organizations/Code for America.json"}}}}}