{"data":{"type":"project","id":"Open Elections/openelections-sources-mo","links":{"self":"/organizations/Open Elections/projects/openelections-sources-mo.json"},"attributes":{"code_url":"https://github.com/openelections/openelections-sources-mo","description":"Original source files from Missouri elections","git_branch":"master","git_url":"git://github.com/openelections/openelections-sources-mo.git","last_pushed_within":"year","name":"openelections-sources-mo","open_issues_within":10,"organization_name":"Open Elections"},"relationships":{"organization":{"data":{"type":"organization","id":"Open Elections"},"links":{"related":"/organizations/Open Elections.json"}}}}}