{"data":{"type":"project","id":"Code for Anchorage/courtbot-admin","links":{"self":"/organizations/Code for Anchorage/projects/courtbot-admin.json"},"attributes":{"code_url":"https://github.com/codeforanchorage/courtbot-admin","description":"Admin iterface for viewing Courtbot logs and history.","git_branch":"master","git_url":"git://github.com/codeforanchorage/courtbot-admin.git","last_pushed_within":"over_a_year","name":"courtbot-admin","organization_name":"Code for Anchorage"},"relationships":{"organization":{"data":{"type":"organization","id":"Code for Anchorage"},"links":{"related":"/organizations/Code for Anchorage.json"}}}}}