{"data":{"type":"project","id":"Open Savannah/cap_app","links":{"self":"/organizations/Open Savannah/projects/cap_app.json"},"attributes":{"code_url":"https://github.com/opensavannah/cap_app","description":"Online Application for Chatham Apprentice Program ","git_branch":"master","git_url":"git://github.com/opensavannah/cap_app.git","last_pushed_within":"over_a_year","name":"cap_app","organization_name":"Open Savannah"},"relationships":{"organization":{"data":{"type":"organization","id":"Open Savannah"},"links":{"related":"/organizations/Open Savannah.json"}}}}}