{"data":{"type":"project","id":"Open Savannah/wiki","links":{"self":"/organizations/Open Savannah/projects/wiki.json"},"attributes":{"code_url":"https://github.com/opensavannah/wiki","description":"Brigade knowledge-sharing/documenting wiki","git_branch":"master","git_url":"git://github.com/opensavannah/wiki.git","last_pushed_within":"over_a_year","link_url":"http://wiki.opensavannah.org","name":"wiki","organization_name":"Open Savannah"},"relationships":{"organization":{"data":{"type":"organization","id":"Open Savannah"},"links":{"related":"/organizations/Open Savannah.json"}}}}}