{"data":{"type":"project","id":"Code for Philly/Reclaim_Philly","links":{"self":"/organizations/Code for Philly/projects/Reclaim_Philly.json"},"attributes":{"code_url":"https://github.com/ReclaimPhilly","description":"A way to help revitalize, renew, and reclaim Philadelphia's abandoned properties.","link_url":"http://reclaimphilly.org","name":"Reclaim_Philly","organization_name":"Code for Philly","status":"Drifting"},"relationships":{"organization":{"data":{"type":"organization","id":"Code for Philly"},"links":{"related":"/organizations/Code for Philly.json"}}}}}