{"data":{"type":"project","id":"Open Lexington/BusAlertAndroidApp","links":{"self":"/organizations/Open Lexington/projects/BusAlertAndroidApp.json"},"attributes":{"code_url":"https://github.com/openlexington/BusAlertAndroidApp","description":"BusAlert app for Android","git_branch":"master","git_url":"git://github.com/openlexington/BusAlertAndroidApp.git","last_pushed_within":"over_a_year","link_url":"http://ukopenlexingtonseniordesign.github.io/","name":"BusAlertAndroidApp","organization_name":"Open Lexington"},"relationships":{"organization":{"data":{"type":"organization","id":"Open Lexington"},"links":{"related":"/organizations/Open Lexington.json"}}}}}