{"data":{"type":"project","id":"Smart Chicago Collaborative/cutgroup-signups","links":{"self":"/organizations/Smart Chicago Collaborative/projects/cutgroup-signups.json"},"attributes":{"code_url":"https://github.com/smartchicago/cutgroup-signups","description":"Small app to handle CUT Group signups","git_branch":"master","git_url":"git://github.com/smartchicago/cutgroup-signups.git","last_pushed_within":"over_a_year","name":"cutgroup-signups","organization_name":"Smart Chicago Collaborative"},"relationships":{"organization":{"data":{"type":"organization","id":"Smart Chicago Collaborative"},"links":{"related":"/organizations/Smart Chicago Collaborative.json"}}}}}