{"data":{"type":"project","id":"Code for Atlanta/atl-citygram-data","links":{"self":"/organizations/Code for Atlanta/projects/atl-citygram-data.json"},"attributes":{"code_url":"https://github.com/codeforatlanta/atl-citygram-data","description":"Scraping & Collecting data to plug in to the Atlanta Citygram app","git_branch":"master","git_url":"git://github.com/codeforatlanta/atl-citygram-data.git","last_pushed_within":"over_a_year","name":"atl-citygram-data","open_issues_within":10,"organization_name":"Code for Atlanta"},"relationships":{"organization":{"data":{"type":"organization","id":"Code for Atlanta"},"links":{"related":"/organizations/Code for Atlanta.json"}}}}}