{"data":{"type":"project","id":"Code for Tulsa/snap-screener","links":{"self":"/organizations/Code for Tulsa/projects/snap-screener.json"},"attributes":{"code_url":"https://github.com/codefortulsa/snap-screener","description":"Screener for SNAP. Built in partnership with Hunger Free Oklahaoma and TPS. Very special thanks to volunteers Travis Miller, Cody Walinciak, Kendall Wertz, and Chris Doe.","git_branch":"master","git_url":"git://github.com/codefortulsa/snap-screener.git","last_pushed_within":"year","link_url":"https://snap-screener-ok.web.app/","name":"snap-screener","open_issues_within":10,"organization_name":"Code for Tulsa","topics":["civictechindex","code-for-america","code-for-tulsa","food-security","snap","social-safety-net"]},"relationships":{"organization":{"data":{"type":"organization","id":"Code for Tulsa"},"links":{"related":"/organizations/Code for Tulsa.json"}}}}}