{"data":{"type":"project","id":"Code for Tulsa/water-in-the-river","links":{"self":"/organizations/Code for Tulsa/projects/water-in-the-river.json"},"attributes":{"code_url":"https://github.com/codefortulsa/water-in-the-river","description":"A simple app that checks data from USGS, USACE, and SWPA to determine if (and when) there is water in the Tulsa Riverside stretch of the Arkansas River.","git_branch":"master","git_url":"git://github.com/codefortulsa/water-in-the-river.git","last_pushed_within":"over_a_year","link_url":"http://istherewaterintheriver.com","name":"water-in-the-river","open_issues_within":10,"organization_name":"Code for Tulsa"},"relationships":{"organization":{"data":{"type":"organization","id":"Code for Tulsa"},"links":{"related":"/organizations/Code for Tulsa.json"}}}}}