{"data":{"type":"project","id":"Code for Curitiba/nfe-biblioteca","links":{"self":"/organizations/Code for Curitiba/projects/nfe-biblioteca.json"},"attributes":{"code_url":"https://github.com/CodeForCuritiba/nfe-biblioteca","description":"API em javascript para carregar dados sobre Nota Fiscal de Consumidor Eletrônica através do link exibido no DANFE","git_branch":"master","git_url":"git://github.com/CodeForCuritiba/nfe-biblioteca.git","last_pushed_within":"over_a_year","name":"nfe-biblioteca","organization_name":"Code for Curitiba"},"relationships":{"organization":{"data":{"type":"organization","id":"Code for Curitiba"},"links":{"related":"/organizations/Code for Curitiba.json"}}}}}