{"data":{"type":"project","id":"Code for Upper Valley/food_resources","links":{"self":"/organizations/Code for Upper Valley/projects/food_resources.json"},"attributes":{"code_url":"https://github.com/codeforUV/food_resources","description":"A project that aims to increase food access for residents of the Upper Valley region of VT/NH","git_branch":"master","git_url":"git://github.com/codeforUV/food_resources.git","last_pushed_within":"month","link_url":"https://food-resources.herokuapp.com","name":"food_resources","open_issues_within":100,"organization_name":"Code for Upper Valley","topics":["codeforamerica","food-access","food-resources","new-hampshire","ruby-on-rails","tailwindcss","upper-valley","vermont"]},"relationships":{"organization":{"data":{"type":"organization","id":"Code for Upper Valley"},"links":{"related":"/organizations/Code for Upper Valley.json"}}}}}