{"data":{"type":"project","id":"KC Digital Drive/clear-my-record-front-end-nuxt","links":{"self":"/organizations/KC Digital Drive/projects/clear-my-record-front-end-nuxt.json"},"attributes":{"code_url":"https://github.com/codeforkansascity/clear-my-record-front-end-nuxt","description":"Application Code for Clear My Record, an application to assist people the process of expunging their criminal convictions.","git_branch":"develop","git_url":"git://github.com/codeforkansascity/clear-my-record-front-end-nuxt.git","last_pushed_within":"over_a_year","link_url":"http://cmr.codeforkc.org","name":"clear-my-record-front-end-nuxt","open_issues_within":10,"organization_name":"KC Digital Drive"},"relationships":{"organization":{"data":{"type":"organization","id":"KC Digital Drive"},"links":{"related":"/organizations/KC Digital Drive.json"}}}}}