{"data":{"type":"project","id":"KC Digital Drive/kcmedregistry","links":{"self":"/organizations/KC Digital Drive/projects/kcmedregistry.json"},"attributes":{"code_url":"https://github.com/codeforkansascity/kcmedregistry","description":"KC Medicine Registry","git_branch":"master","git_url":"git://github.com/codeforkansascity/kcmedregistry.git","last_pushed_within":"over_a_year","name":"kcmedregistry","organization_name":"KC Digital Drive"},"relationships":{"organization":{"data":{"type":"organization","id":"KC Digital Drive"},"links":{"related":"/organizations/KC Digital Drive.json"}}}}}