{"data":{"type":"project","id":"Code for Croatia/codeforcroatia.org","links":{"self":"/organizations/Code for Croatia/projects/codeforcroatia.org.json"},"attributes":{"code_url":"https://github.com/codeforcroatia/codeforcroatia.org","description":"Extended project of Laddr for Code for Croatia website","git_branch":"master","git_url":"git://github.com/codeforcroatia/codeforcroatia.org.git","last_pushed_within":"week","link_url":"https://codeforcroatia.org","name":"codeforcroatia.org","open_issues_within":100,"organization_name":"Code for Croatia","topics":["codeforcroatia","laddr"]},"relationships":{"organization":{"data":{"type":"organization","id":"Code for Croatia"},"links":{"related":"/organizations/Code for Croatia.json"}}}}}