{"data":{"type":"project","id":"Code for Croatia/discourse","links":{"self":"/organizations/Code for Croatia/projects/discourse.json"},"attributes":{"code_url":"https://github.com/codeforcroatia/discourse","description":"A platform for community discussion. Free, open, simple.","git_branch":"master","git_url":"git://github.com/codeforcroatia/discourse.git","link_url":"http://diskurs.open.hr","name":"discourse"},"relationships":{"organization":{"data":{"type":"organization","id":"Code for Croatia"},"links":{"related":"/organizations/Code for Croatia.json"}}}}}