{"data":{"type":"project","id":"mySociety/alaveteli-production-vm","links":{"self":"/organizations/mySociety/projects/alaveteli-production-vm.json"},"attributes":{"code_url":"https://github.com/mysociety/alaveteli-production-vm","description":"VM with Alaveteli installed in production mode for testing.","git_branch":"master","git_url":"git://github.com/mysociety/alaveteli-production-vm.git","last_pushed_within":"over_a_year","name":"alaveteli-production-vm","organization_name":"mySociety","topics":["alaveteli"]},"relationships":{"organization":{"data":{"type":"organization","id":"mySociety"},"links":{"related":"/organizations/mySociety.json"}}}}}