{"data":{"type":"project","id":"mySociety/popolo-name-resolver","links":{"self":"/organizations/mySociety/projects/popolo-name-resolver.json"},"attributes":{"code_url":"https://github.com/mysociety/popolo-name-resolver","description":"A name resolver library for Popolo people data based on django-popolo","git_branch":"master","git_url":"git://github.com/mysociety/popolo-name-resolver.git","last_pushed_within":"over_a_year","name":"popolo-name-resolver","open_issues_within":10,"organization_name":"mySociety"},"relationships":{"organization":{"data":{"type":"organization","id":"mySociety"},"links":{"related":"/organizations/mySociety.json"}}}}}