{"data":{"type":"project","id":"Code for DC/dc_bus_stuff","links":{"self":"/organizations/Code for DC/projects/dc_bus_stuff.json"},"attributes":{"code_url":"https://github.com/codefordc/dc_bus_stuff","description":"looking at DC bustime data","git_branch":"master","git_url":"git://github.com/codefordc/dc_bus_stuff.git","last_pushed_within":"over_a_year","name":"dc_bus_stuff","organization_name":"Code for DC"},"relationships":{"organization":{"data":{"type":"organization","id":"Code for DC"},"links":{"related":"/organizations/Code for DC.json"}}}}}