{"data":{"type":"project","id":"Code for DC/finda","links":{"self":"/organizations/Code for DC/projects/finda.json"},"attributes":{"code_url":"https://github.com/codefordc/finda","description":"#BaltimoreLunch config of Find-a","git_branch":"gh-pages","git_url":"git://github.com/codefordc/finda.git","last_pushed_within":"over_a_year","name":"finda","organization_name":"Code for DC"},"relationships":{"organization":{"data":{"type":"organization","id":"Code for DC"},"links":{"related":"/organizations/Code for DC.json"}}}}}