{"data":{"type":"project","id":"Code for DC/optoro-data-help","links":{"self":"/organizations/Code for DC/projects/optoro-data-help.json"},"attributes":{"code_url":"https://github.com/codefordc/optoro-data-help","description":"A central location for our friends at Optoro to find our data sets","git_branch":"master","git_url":"git://github.com/codefordc/optoro-data-help.git","last_pushed_within":"over_a_year","name":"optoro-data-help","organization_name":"Code for DC"},"relationships":{"organization":{"data":{"type":"organization","id":"Code for DC"},"links":{"related":"/organizations/Code for DC.json"}}}}}