{"data":{"type":"project","id":"Code for DC/slack-doorbell","links":{"self":"/organizations/Code for DC/projects/slack-doorbell.json"},"attributes":{"code_url":"https://github.com/codefordc/slack-doorbell","description":"\"Doorbell\", so members can text Twilio and it alerts us all on Slack","git_branch":"master","git_url":"git://github.com/codefordc/slack-doorbell.git","last_pushed_within":"over_a_year","name":"slack-doorbell","organization_name":"Code for DC"},"relationships":{"organization":{"data":{"type":"organization","id":"Code for DC"},"links":{"related":"/organizations/Code for DC.json"}}}}}