{"data":{"type":"project","id":"OK Lab M端nster/digitransit-graphiql","links":{"self":"/organizations/OK Lab M端nster/projects/digitransit-graphiql.json"},"attributes":{"code_url":"https://github.com/codeformuenster/digitransit-graphiql","git_branch":"master","git_url":"git://github.com/codeformuenster/digitransit-graphiql.git","name":"digitransit-graphiql"},"relationships":{"organization":{"data":{"type":"organization","id":"OK Lab M端nster"},"links":{"related":"/organizations/OK Lab M端nster.json"}}}}}