{"data":{"type":"project","id":"OK Lab Münster/logstash-filter-geocoder","links":{"self":"/organizations/OK Lab Münster/projects/logstash-filter-geocoder.json"},"attributes":{"code_url":"https://github.com/codeformuenster/logstash-filter-geocoder","description":"Logstash filter that converts strings (addresses) into coordinates using geocoder gem","git_branch":"master","git_url":"git://github.com/codeformuenster/logstash-filter-geocoder.git","last_pushed_within":"over_a_year","name":"logstash-filter-geocoder","organization_name":"OK Lab Münster"},"relationships":{"organization":{"data":{"type":"organization","id":"OK Lab Münster"},"links":{"related":"/organizations/OK Lab Münster.json"}}}}}