{"data":{"type":"project","id":"OK Lab Münster/open-data-karte-muenster","links":{"self":"/organizations/OK Lab Münster/projects/open-data-karte-muenster.json"},"attributes":{"code_url":"https://github.com/codeformuenster/open-data-karte-muenster","description":"Visualisierung der Stadtteil-Statistiken der Stadt Münster (Gehälter, Arbeitslose, etc..).","git_branch":"master","git_url":"git://github.com/codeformuenster/open-data-karte-muenster.git","last_pushed_within":"over_a_year","link_url":"http://codeformuenster.org/open-data-karte-muenster/","name":"open-data-karte-muenster","organization_name":"OK Lab Münster"},"relationships":{"organization":{"data":{"type":"organization","id":"OK Lab Münster"},"links":{"related":"/organizations/OK Lab Münster.json"}}}}}