{"data":{"type":"project","id":"OK Lab M端nster/parking-decks-muenster","links":{"self":"/organizations/OK Lab M端nster/projects/parking-decks-muenster.json"},"attributes":{"code_url":"https://github.com/codeformuenster/parking-decks-muenster","git_branch":"master","git_url":"git://github.com/codeformuenster/parking-decks-muenster.git","link_url":"https://github.com/codeformuenster/parking-decks-muenster","name":"parking-decks-muenster"},"relationships":{"organization":{"data":{"type":"organization","id":"OK Lab M端nster"},"links":{"related":"/organizations/OK Lab M端nster.json"}}}}}