{"data":{"type":"project","id":"OK Lab Münster/wahlprogramme2014","links":{"self":"/organizations/OK Lab Münster/projects/wahlprogramme2014.json"},"attributes":{"code_url":"https://github.com/codeformuenster/wahlprogramme2014","description":"Wahlprogramme der Parteien zur Kommunalwahl 2014 in maschinenlesbarer Form.","git_branch":"master","git_url":"git://github.com/codeformuenster/wahlprogramme2014.git","last_pushed_within":"over_a_year","link_url":"https://github.com/codeformuenster/wahlprogramme2014","name":"wahlprogramme2014","open_issues_within":10,"organization_name":"OK Lab Münster"},"relationships":{"organization":{"data":{"type":"organization","id":"OK Lab Münster"},"links":{"related":"/organizations/OK Lab Münster.json"}}}}}