{"data":{"type":"project","id":"Code for San Francisco/lighten-api","links":{"self":"/organizations/Code for San Francisco/projects/lighten-api.json"},"attributes":{"code_url":"https://github.com/sfbrigade/lighten-api","git_branch":"master","git_url":"git://github.com/sfbrigade/lighten-api.git","link_url":"https://github.com/sfbrigade/lighten/wiki","name":"lighten-api"},"relationships":{"organization":{"data":{"type":"organization","id":"Code for San Francisco"},"links":{"related":"/organizations/Code for San Francisco.json"}}}}}