{"data":{"type":"project","id":"Code for San Francisco/lighten","links":{"self":"/organizations/Code for San Francisco/projects/lighten.json"},"attributes":{"code_url":"https://github.com/sfbrigade/lighten","git_branch":"master","git_url":"git://github.com/sfbrigade/lighten.git","link_url":"https://github.com/sfbrigade/lighten/wiki","name":"lighten"},"relationships":{"organization":{"data":{"type":"organization","id":"Code for San Francisco"},"links":{"related":"/organizations/Code for San Francisco.json"}}}}}