{"data":{"type":"project","id":"Code for RVA/codeforrva","links":{"self":"/organizations/Code for RVA/projects/codeforrva.json"},"attributes":{"code_url":"https://github.com/codeforrva/codeforrva","description":"Wordpress Site for CodeForRVA.org","git_branch":"master","git_url":"git://github.com/codeforrva/codeforrva.git","last_pushed_within":"over_a_year","name":"codeforrva","organization_name":"Code for RVA"},"relationships":{"organization":{"data":{"type":"organization","id":"Code for RVA"},"links":{"related":"/organizations/Code for RVA.json"}}}}}