{"data":{"type":"project","id":"Open NC Collaborative/park-locator","links":{"self":"/organizations/Open NC Collaborative/projects/park-locator.json"},"attributes":{"code_url":"https://github.com/Open-NC/park-locator","git_branch":"master","git_url":"git://github.com/Open-NC/park-locator.git","link_url":"https://maps.raleighnc.gov/parklocator","name":"park-locator"},"relationships":{"organization":{"data":{"type":"organization","id":"Open NC Collaborative"},"links":{"related":"/organizations/Open NC Collaborative.json"}}}}}