{"data":{"type":"project","id":"Open Nebraska/renters-help","links":{"self":"/organizations/Open Nebraska/projects/renters-help.json"},"attributes":{"code_url":"https://github.com/opennebraska/renters-help","git_branch":"master","git_url":"git://github.com/opennebraska/renters-help.git","last_pushed_within":"week","link_url":"https://opennebraska.github.io/renters-help/","name":"renters-help"},"relationships":{"organization":{"data":{"type":"organization","id":"Open Nebraska"},"links":{"related":"/organizations/Open Nebraska.json"}}}}}